led_cube_view/__init__.py
led_cube_view/config/10x10x10_cube.json
led_cube_view/config/11x11x11_cube.json
led_cube_view/config/12x12x12_cube.json
led_cube_view/config/13x13x13_cube.json
led_cube_view/config/14x14x14_cube.json
led_cube_view/config/15x15x15_cube.json
led_cube_view/config/16x16x16_cube.json
led_cube_view/config/2x2x2_cube.json
led_cube_view/config/3x3x3_cube.json
led_cube_view/config/4x4x4_cube.json
led_cube_view/config/5x5x5_cube.json
led_cube_view/config/6x6x6_cube.json
led_cube_view/config/7x7x7_cube.json
led_cube_view/config/8x8x8_cube.json
led_cube_view/config/9x9x9_cube.json
led_cube_view/led.stl
led_cube_view/led_cube_view.py
led_cube_view/tools/__init__.py
led_cube_view/tools/demo.py
led_cube_view-1.1.2.dist-info/LICENSE
led_cube_view-1.1.2.dist-info/WHEEL
led_cube_view-1.1.2.dist-info/METADATA
led_cube_view-1.1.2.dist-info/RECORD
